gaitsetpy/__init__.py
gaitsetpy/_version.html
gaitsetpy/_version.py
gaitsetpy/classification.html
gaitsetpy/core.html
gaitsetpy/dataset.html
gaitsetpy/eda.html
gaitsetpy/features.html
gaitsetpy/main.html
gaitsetpy/main.py
gaitsetpy/preprocessing.html
gaitsetpy/utils.html
gaitsetpy/utils.py
gaitsetpy/classification/__init__.py
gaitsetpy/classification/models.html
gaitsetpy/classification/utils.html
gaitsetpy/classification/models/__init__.py
gaitsetpy/classification/models/bilstm.html
gaitsetpy/classification/models/bilstm.py
gaitsetpy/classification/models/cnn.html
gaitsetpy/classification/models/cnn.py
gaitsetpy/classification/models/gnn.html
gaitsetpy/classification/models/gnn.py
gaitsetpy/classification/models/lstm.html
gaitsetpy/classification/models/lstm.py
gaitsetpy/classification/models/mlp.html
gaitsetpy/classification/models/mlp.py
gaitsetpy/classification/models/random_forest.html
gaitsetpy/classification/models/random_forest.py
gaitsetpy/classification/utils/__init__.py
gaitsetpy/classification/utils/dataset.html
gaitsetpy/classification/utils/dataset.py
gaitsetpy/classification/utils/eval.html
gaitsetpy/classification/utils/eval.py
gaitsetpy/classification/utils/preprocess.html
gaitsetpy/classification/utils/preprocess.py
gaitsetpy/classification/utils/train.html
gaitsetpy/classification/utils/train.py
gaitsetpy/classification/weights/random_forest_model_40_10.pkl
gaitsetpy/core/__init__.py
gaitsetpy/core/base_classes.html
gaitsetpy/core/base_classes.py
gaitsetpy/core/managers.html
gaitsetpy/core/managers.py
gaitsetpy/dataset/__init__.py
gaitsetpy/dataset/arduous.html
gaitsetpy/dataset/arduous.py
gaitsetpy/dataset/daphnet.html
gaitsetpy/dataset/daphnet.py
gaitsetpy/dataset/harup.html
gaitsetpy/dataset/harup.py
gaitsetpy/dataset/mobifall.html
gaitsetpy/dataset/mobifall.py
gaitsetpy/dataset/physionet.html
gaitsetpy/dataset/physionet.py
gaitsetpy/dataset/urfall.html
gaitsetpy/dataset/urfall.py
gaitsetpy/dataset/utils.html
gaitsetpy/dataset/utils.py
gaitsetpy-0.2.4.dist-info/licenses/LICENSE
gaitsetpy-0.2.4.dist-info/METADATA
gaitsetpy-0.2.4.dist-info/WHEEL
gaitsetpy-0.2.4.dist-info/top_level.txt
gaitsetpy-0.2.4.dist-info/RECORD
