Metadata-Version: 2.4
Name: gaitsetpy
Version: 0.2.4
Summary: A Python package for gait analysis using sensor data.
Author-email: Alohomora Labs <aharshit123456@gmail.com>
License: GPL-3.0
Project-URL: Homepage, https://github.com/Alohomora-Labs/gaitSetPy
Project-URL: Documentation, https://alohomora-labs.github.io/gaitSetPy/gaitsetpy.html
Project-URL: Repository, https://github.com/Alohomora-Labs/gaitSetPy
Project-URL: Issues, https://github.com/Alohomora-Labs/gaitSetPy/issues
Keywords: gait,analysis,sensors,machine-learning,health
Classifier: Development Status :: 4 - Beta
Classifier: Intended Audience :: Science/Research
Classifier: License :: OSI Approved :: GNU General Public License v3 (GPLv3)
Classifier: Operating System :: OS Independent
Classifier: Programming Language :: Python :: 3
Classifier: Programming Language :: Python :: 3.8
Classifier: Programming Language :: Python :: 3.9
Classifier: Programming Language :: Python :: 3.10
Classifier: Programming Language :: Python :: 3.11
Classifier: Topic :: Scientific/Engineering
Requires-Python: >=3.8
License-File: LICENSE
Requires-Dist: numpy
Requires-Dist: pandas
Requires-Dist: scipy
Requires-Dist: requests
Requires-Dist: statsmodels
Requires-Dist: matplotlib
Requires-Dist: scikit-learn
Requires-Dist: joblib
Requires-Dist: tqdm
Provides-Extra: deep-learning
Requires-Dist: torch>=1.9.0; extra == "deep-learning"
Provides-Extra: all
Requires-Dist: torch>=1.9.0; extra == "all"
Provides-Extra: dev
Requires-Dist: pytest>=7.0; extra == "dev"
Requires-Dist: pytest-cov>=4.0; extra == "dev"
Requires-Dist: black>=24.0; extra == "dev"
Requires-Dist: isort>=5.0; extra == "dev"
Requires-Dist: flake8>=6.0; extra == "dev"
Requires-Dist: mypy>=1.0; extra == "dev"
Requires-Dist: pre-commit>=3.0; extra == "dev"
Requires-Dist: bandit>=1.7; extra == "dev"
Dynamic: license-file
